persistlit/__init__.py
persistlit/py.typed
persistlit-0.1.1.dist-info/METADATA
persistlit-0.1.1.dist-info/WHEEL
persistlit-0.1.1.dist-info/licenses/LICENSE
persistlit-0.1.1.dist-info/RECORD
