Metadata-Version: 2.4
Name: persistlit
Version: 0.1.1
Summary: Better persistent streamlit widgets
Author-email: jakeayres <jake_ayres@hotmail.co.uk>
License-File: LICENSE
Requires-Python: >=3.13
Requires-Dist: streamlit>=1.45.1
